{
  "timestamp": "2026-05-04T20:21:26.410848",
  "files": [
    {
      "file_path": "/Volumes/project/private/idea-workflow/backend/src/modules/execution-engine/execution-engine.service.spec.ts",
      "change_type": "Review",
      "file_extension": "ts"
    },
    {
      "file_path": "/Volumes/project/private/idea-workflow/backend/src/modules/execution-engine/execution-engine.service.ts",
      "change_type": "Review",
      "file_extension": "ts"
    },
    {
      "file_path": "/Volumes/project/private/idea-workflow/spec/5-system/6-websocket-protocol.md",
      "change_type": "Review",
      "file_extension": "md"
    }
  ],
  "total_elapsed_seconds": 355.41,
  "agents": [
    {
      "name": "database",
      "status": "success",
      "elapsed_seconds": 19.07
    },
    {
      "name": "documentation",
      "status": "success",
      "elapsed_seconds": 33.01
    },
    {
      "name": "performance",
      "status": "success",
      "elapsed_seconds": 45.43
    },
    {
      "name": "concurrency",
      "status": "success",
      "elapsed_seconds": 47.77
    },
    {
      "name": "maintainability",
      "status": "success",
      "elapsed_seconds": 54.94
    },
    {
      "name": "dependency",
      "status": "success",
      "elapsed_seconds": 58.68
    },
    {
      "name": "testing",
      "status": "success",
      "elapsed_seconds": 60.49
    },
    {
      "name": "api_contract",
      "status": "success",
      "elapsed_seconds": 60.62
    },
    {
      "name": "scope",
      "status": "success",
      "elapsed_seconds": 64.82
    },
    {
      "name": "security",
      "status": "success",
      "elapsed_seconds": 73.42
    },
    {
      "name": "side_effect",
      "status": "success",
      "elapsed_seconds": 78.81
    },
    {
      "name": "requirement",
      "status": "success",
      "elapsed_seconds": 86.06
    },
    {
      "name": "architecture",
      "status": "success",
      "elapsed_seconds": 97.45
    }
  ]
}