{
  "timestamp": "2026-06-05T14:05:22.267041",
  "files": [
    {
      "file_path": "codebase/backend/src/nodes/ai/ai-agent/ai-agent.handler.ts",
      "change_type": "Review",
      "file_extension": "ts"
    },
    {
      "file_path": "codebase/backend/src/nodes/ai/ai-agent/ai-agent.schema.ts",
      "change_type": "Review",
      "file_extension": "ts"
    },
    {
      "file_path": "codebase/backend/src/nodes/ai/information-extractor/information-extractor.component.ts",
      "change_type": "Review",
      "file_extension": "ts"
    },
    {
      "file_path": "codebase/backend/src/nodes/ai/information-extractor/information-extractor.handler.ts",
      "change_type": "Review",
      "file_extension": "ts"
    },
    {
      "file_path": "codebase/backend/src/nodes/ai/information-extractor/information-extractor.schema.ts",
      "change_type": "Review",
      "file_extension": "ts"
    },
    {
      "file_path": "codebase/backend/src/nodes/ai/information-extractor/information-extractor.thread.spec.ts",
      "change_type": "Review",
      "file_extension": "ts"
    },
    {
      "file_path": "codebase/backend/src/nodes/ai/shared/conversation-context-injection.spec.ts",
      "change_type": "Review",
      "file_extension": "ts"
    },
    {
      "file_path": "codebase/backend/src/nodes/ai/shared/conversation-context-injection.ts",
      "change_type": "Review",
      "file_extension": "ts"
    },
    {
      "file_path": "codebase/backend/src/nodes/ai/shared/conversation-context-schema.ts",
      "change_type": "Review",
      "file_extension": "ts"
    },
    {
      "file_path": "codebase/backend/src/nodes/ai/text-classifier/text-classifier.handler.ts",
      "change_type": "Review",
      "file_extension": "ts"
    },
    {
      "file_path": "codebase/backend/src/nodes/ai/text-classifier/text-classifier.schema.ts",
      "change_type": "Review",
      "file_extension": "ts"
    },
    {
      "file_path": "codebase/backend/src/nodes/ai/text-classifier/text-classifier.thread.spec.ts",
      "change_type": "Review",
      "file_extension": "ts"
    },
    {
      "file_path": "codebase/frontend/src/content/docs/02-nodes/ai.en.mdx",
      "change_type": "Review",
      "file_extension": "mdx"
    },
    {
      "file_path": "codebase/frontend/src/content/docs/02-nodes/ai.mdx",
      "change_type": "Review",
      "file_extension": "mdx"
    },
    {
      "file_path": "plan/in-progress/memory-autoinject-extend.md",
      "change_type": "Review",
      "file_extension": "md"
    },
    {
      "file_path": "spec/4-nodes/3-ai/0-common.md",
      "change_type": "Review",
      "file_extension": "md"
    },
    {
      "file_path": "spec/4-nodes/3-ai/1-ai-agent.md",
      "change_type": "Review",
      "file_extension": "md"
    },
    {
      "file_path": "spec/4-nodes/3-ai/2-text-classifier.md",
      "change_type": "Review",
      "file_extension": "md"
    },
    {
      "file_path": "spec/4-nodes/3-ai/3-information-extractor.md",
      "change_type": "Review",
      "file_extension": "md"
    },
    {
      "file_path": "spec/conventions/conversation-thread.md",
      "change_type": "Review",
      "file_extension": "md"
    }
  ],
  "agents": [
    "security",
    "performance",
    "architecture",
    "requirement",
    "scope",
    "side_effect",
    "maintainability",
    "testing",
    "documentation",
    "dependency",
    "database",
    "concurrency",
    "api_contract",
    "user_guide_sync"
  ],
  "route_mode": "auto",
  "agents_explicit": false,
  "agents_forced": [
    "documentation",
    "maintainability",
    "requirement",
    "scope",
    "security",
    "side_effect",
    "testing"
  ]
}