{
  "timestamp": "2026-06-03T18:43:09.205555",
  "files": [
    {
      "file_path": "codebase/frontend/src/lib/i18n/dict/ko/statistics.ts",
      "change_type": "Review",
      "file_extension": "ts"
    },
    {
      "file_path": "codebase/frontend/src/lib/i18n/dict/ko/triggers.ts",
      "change_type": "Review",
      "file_extension": "ts"
    },
    {
      "file_path": "codebase/frontend/src/lib/i18n/dict/ko/workflows.ts",
      "change_type": "Review",
      "file_extension": "ts"
    },
    {
      "file_path": "codebase/packages/node-summary/src/__tests__/evaluator.spec.ts",
      "change_type": "Review",
      "file_extension": "ts"
    },
    {
      "file_path": "codebase/packages/node-summary/src/evaluator.ts",
      "change_type": "Review",
      "file_extension": "ts"
    }
  ],
  "agents": [
    "security",
    "performance",
    "architecture",
    "requirement",
    "scope",
    "side_effect",
    "maintainability",
    "testing",
    "documentation",
    "dependency",
    "database",
    "concurrency",
    "api_contract",
    "user_guide_sync"
  ],
  "route_mode": "auto",
  "agents_explicit": false,
  "agents_forced": [
    "maintainability",
    "requirement",
    "scope",
    "security",
    "side_effect",
    "testing"
  ]
}