{
  "timestamp": "2026-06-03T09:30:50.804001",
  "files": [
    {
      "file_path": "codebase/backend/src/nodes/data/code/code.handler.spec.ts",
      "change_type": "Review",
      "file_extension": "ts"
    },
    {
      "file_path": "codebase/backend/src/nodes/data/code/code.handler.ts",
      "change_type": "Review",
      "file_extension": "ts"
    },
    {
      "file_path": "codebase/backend/src/nodes/data/code/code.schema.spec.ts",
      "change_type": "Review",
      "file_extension": "ts"
    },
    {
      "file_path": "codebase/backend/src/nodes/data/code/code.schema.ts",
      "change_type": "Review",
      "file_extension": "ts"
    }
  ],
  "agents": [
    "security",
    "performance",
    "architecture",
    "requirement",
    "scope",
    "side_effect",
    "maintainability",
    "testing",
    "documentation",
    "dependency",
    "database",
    "concurrency",
    "api_contract",
    "user_guide_sync"
  ],
  "route_mode": "auto",
  "agents_explicit": false,
  "agents_forced": [
    "maintainability",
    "requirement",
    "scope",
    "security",
    "side_effect",
    "testing"
  ]
}