{
  "timestamp": "2026-06-05T00:12:34.490296",
  "files": [
    {
      "file_path": "codebase/backend/src/modules/agent-memory/agent-memory.service.spec.ts",
      "change_type": "Review",
      "file_extension": "ts"
    },
    {
      "file_path": "codebase/backend/src/modules/agent-memory/agent-memory.service.ts",
      "change_type": "Review",
      "file_extension": "ts"
    },
    {
      "file_path": "codebase/backend/src/modules/agent-memory/entities/agent-memory.entity.ts",
      "change_type": "Review",
      "file_extension": "ts"
    },
    {
      "file_path": "codebase/backend/src/modules/agent-memory/queues/agent-memory-extraction.processor.ts",
      "change_type": "Review",
      "file_extension": "ts"
    },
    {
      "file_path": "codebase/backend/src/modules/agent-memory/queues/agent-memory-extraction.queue.ts",
      "change_type": "Review",
      "file_extension": "ts"
    },
    {
      "file_path": "codebase/backend/src/nodes/ai/ai-agent/ai-agent.handler.ts",
      "change_type": "Review",
      "file_extension": "ts"
    },
    {
      "file_path": "codebase/backend/src/nodes/ai/ai-agent/ai-agent.memory.spec.ts",
      "change_type": "Review",
      "file_extension": "ts"
    },
    {
      "file_path": "codebase/backend/src/nodes/ai/ai-agent/ai-agent.schema.ts",
      "change_type": "Review",
      "file_extension": "ts"
    },
    {
      "file_path": "spec/1-data-model.md",
      "change_type": "Review",
      "file_extension": "md"
    },
    {
      "file_path": "spec/4-nodes/3-ai/1-ai-agent.md",
      "change_type": "Review",
      "file_extension": "md"
    },
    {
      "file_path": "spec/5-system/17-agent-memory.md",
      "change_type": "Review",
      "file_extension": "md"
    }
  ],
  "agents": [
    "security",
    "performance",
    "architecture",
    "requirement",
    "scope",
    "side_effect",
    "maintainability",
    "testing",
    "documentation",
    "dependency",
    "database",
    "concurrency",
    "api_contract",
    "user_guide_sync"
  ],
  "route_mode": "auto",
  "agents_explicit": false,
  "agents_forced": [
    "documentation",
    "maintainability",
    "requirement",
    "scope",
    "security",
    "side_effect",
    "testing"
  ]
}