{
  "version": 1,
  "started_at": "2026-05-23T22:29:35Z",
  "summary_items_total": 15,
  "items_resolved_ids": [2, 3, 4, 7, 8, 9, 10, 11, 12, 13],
  "items_pending_ids": [],
  "items_escalated_ids": {
    "1": "false-positive",
    "2-W2": "note-only",
    "5-W5": "note-only",
    "6-W6": "note-only"
  },
  "commits_made": [
    {
      "sha": "f50aa21e83d1c82866e6c1852835617060857e18",
      "summary_ids": ["C2", "W3", "W4", "W7", "W8", "W9", "W10", "W11", "W12", "W13"],
      "scope": "ai-agent"
    }
  ],
  "spec_drafts_pending": [],
  "spec_drafts_applied": [],
  "e2e_attempts": 1,
  "e2e_last_status": "pass",
  "e2e_log_paths": ["_test_logs/e2e-20260523-224939.log"],
  "auto_fix_iterations": {
    "C2": 1
  },
  "escalation_reason": null,
  "last_reset_hint_sec": null
}
